<?xml version = '1.0' encoding = 'UTF-8'?>
<Relation class="oracle.dbtools.crest.model.design.logical.Relation" name="Relation_8" directorySegmentName="seg_0" id="5349C05F-4016-E0CD-D1AD-2A8B0D705DEF">
<createdBy>Robert J</createdBy>
<createdTime>2016-10-13 03:11:52 UTC</createdTime>
<ownerDesignName>rob_design</ownerDesignName>
<engineerTo>
<item key="C5624ED7-0337-AD0F-72C4-40029DF610FB" value="true"/>
</engineerTo>
<sourcePk>95A59669-F35B-7834-3BC1-CDC8E86C0216</sourcePk>
<targetPk>3233DA45-313B-C5C7-6DBF-360B0FF71B99</targetPk>
<identifying>false</identifying>
<optionalSource>true</optionalSource>
<optionalTarget>true</optionalTarget>
<sourceCardinality>1</sourceCardinality>
<sourceEntity>488A7FDA-30AC-C863-01FF-F1DDB499F5CF</sourceEntity>
<targetCardinalityString>1</targetCardinalityString>
<targetEntity>3CD5AD2F-75DF-C322-2D7B-8D2B58D73FEE</targetEntity>
<transferable>true</transferable>
<deleteRule>NO ACTION</deleteRule>
</Relation>